smartexplain/__init__.py
smartexplain/cli.py
smartexplain/explainer.py
smartexplain-0.1.0.dist-info/licenses/LICENSE.txt
smartexplain-0.1.0.dist-info/METADATA
smartexplain-0.1.0.dist-info/WHEEL
smartexplain-0.1.0.dist-info/entry_points.txt
smartexplain-0.1.0.dist-info/top_level.txt
smartexplain-0.1.0.dist-info/RECORD
