Metadata-Version: 2.4
Name: smartexplain
Version: 0.1.0
Summary: Explain Python code like you're 5.
Home-page: https://github.com/Anshuman24singh/SmartExplain
Author: Your Name
Author-email: your.email@example.com
Classifier: Programming Language :: Python :: 3
Classifier: Operating System :: OS Independent
Requires-Python: >=3.7
License-File: LICENSE.txt
Requires-Dist: rich
Requires-Dist: pyperclip
Dynamic: author
Dynamic: author-email
Dynamic: classifier
Dynamic: description
Dynamic: description-content-type
Dynamic: home-page
Dynamic: license-file
Dynamic: requires-dist
Dynamic: requires-python
Dynamic: summary
